[
{"number of samples": "19916", "children": [{"number of samples": "3989", "children": [{"number of samples": "2234", "children": [{"number of samples": "1723", "children": [{"number of samples": "834", "children": [{"number of samples": "409", "name": "predicts 0.39 for 2.1 percent of the points", "percent": 2.05}, {"number of samples": "425", "name": "predicts 0.25 for 2.1 percent of the points", "percent": 2.13}], "name": "Potential > 0.2801", "percent": 4.19}, {"number of samples": "889", "children": [{"number of samples": "506", "name": "predicts 0.2 for 2.5 percent of the points", "percent": 2.54}, {"number of samples": "383", "name": "predicts 0.33 for 1.9 percent of the points", "percent": 1.92}], "name": "Phase > 78.8296", "percent": 4.46}], "name": "Phase > 81.9476", "percent": 8.65}, {"number of samples": "511", "children": [{"number of samples": "6", "children": [{"number of samples": "5", "name": "predicts 0.7 for 0.0 percent of the points", "percent": 0.03}, {"number of samples": "1", "name": "predicts 0.04 for 0.0 percent of the points", "percent": 0.01}], "name": "Potential > 0.2605", "percent": 0.03}, {"number of samples": "505", "children": [{"number of samples": "19", "name": "predicts 0.12 for 0.1 percent of the points", "percent": 0.1}, {"number of samples": "486", "name": "predicts 0.37 for 2.4 percent of the points", "percent": 2.44}], "name": "Phase > 108.6129", "percent": 2.54}], "name": "Phase > 112.9173", "percent": 2.57}], "name": "Potential > 0.2657", "percent": 11.22}, {"number of samples": "1755", "children": [{"number of samples": "339", "children": [{"number of samples": "271", "children": [{"number of samples": "126", "name": "predicts 0.42 for 0.6 percent of the points", "percent": 0.63}, {"number of samples": "145", "name": "predicts 0.58 for 0.7 percent of the points", "percent": 0.73}], "name": "Potential > 0.2511", "percent": 1.36}, {"number of samples": "68", "children": [{"number of samples": "20", "name": "predicts 1.15 for 0.1 percent of the points", "percent": 0.1}, {"number of samples": "48", "name": "predicts 0.68 for 0.2 percent of the points", "percent": 0.24}], "name": "Potential > 0.2435", "percent": 0.34}], "name": "Potential > 0.2444", "percent": 1.7}, {"number of samples": "1416", "children": [{"number of samples": "1223", "children": [{"number of samples": "648", "name": "predicts 0.43 for 3.3 percent of the points", "percent": 3.25}, {"number of samples": "575", "name": "predicts 0.5 for 2.9 percent of the points", "percent": 2.89}], "name": "Potential > 0.2498", "percent": 6.14}, {"number of samples": "193", "children": [{"number of samples": "175", "name": "predicts 0.35 for 0.9 percent of the points", "percent": 0.88}, {"number of samples": "18", "name": "predicts 0.19 for 0.1 percent of the points", "percent": 0.09}], "name": "Phase > 60.0062", "percent": 0.97}], "name": "Phase > 74.3757", "percent": 7.11}], "name": "Phase > 96.4212", "percent": 8.81}], "name": "Potential > 0.2591", "percent": 20.03}, {"number of samples": "15927", "children": [{"number of samples": "15535", "children": [{"number of samples": "6748", "children": [{"number of samples": "2344", "children": [{"number of samples": "893", "name": "predicts 0.72 for 4.5 percent of the points", "percent": 4.48}, {"number of samples": "1451", "name": "predicts 0.79 for 7.3 percent of the points", "percent": 7.29}], "name": "Potential > 0.2202", "percent": 11.77}, {"number of samples": "4404", "children": [{"number of samples": "1328", "name": "predicts 0.57 for 6.7 percent of the points", "percent": 6.67}, {"number of samples": "3076", "name": "predicts 0.65 for 15.4 percent of the points", "percent": 15.44}], "name": "Potential > 0.2271", "percent": 22.11}], "name": "Phase > 94.3977", "percent": 33.88}, {"number of samples": "8787", "children": [{"number of samples": "8704", "children": [{"number of samples": "8162", "name": "predicts 0.82 for 41.0 percent of the points", "percent": 40.98}, {"number of samples": "542", "name": "predicts 0.65 for 2.7 percent of the points", "percent": 2.72}], "name": "Potential > 0.135", "percent": 43.7}, {"number of samples": "83", "children": [{"number of samples": "74", "name": "predicts 1.51 for 0.4 percent of the points", "percent": 0.37}, {"number of samples": "9", "name": "predicts 0.44 for 0.0 percent of the points", "percent": 0.05}], "name": "Potential > 0.1669", "percent": 0.42}], "name": "Phase > 65.284", "percent": 44.12}], "name": "Potential > 0.1994", "percent": 78.0}, {"number of samples": "392", "children": [{"number of samples": "319", "children": [{"number of samples": "293", "children": [{"number of samples": "76", "name": "predicts 0.47 for 0.4 percent of the points", "percent": 0.38}, {"number of samples": "217", "name": "predicts 0.35 for 1.1 percent of the points", "percent": 1.09}], "name": "Potential > 0.1209", "percent": 1.47}, {"number of samples": "26", "children": [{"number of samples": "25", "name": "predicts 0.74 for 0.1 percent of the points", "percent": 0.13}, {"number of samples": "1", "name": "predicts 1.74 for 0.0 percent of the points", "percent": 0.01}], "name": "Potential > 0.1091", "percent": 0.13}], "name": "Phase > 100.8743", "percent": 1.6}, {"number of samples": "73", "name": "predicts 0.0 for 0.4 percent of the points", "percent": 0.37}], "name": "Phase > 35.4587", "percent": 1.97}], "name": "Potential > 0.1238", "percent": 79.97}], "name": "Potential > 0.2423", "percent": 100.0}
]